jmpy/__init__.py
jmpy/cmdline.py
jmpy/encrypt_py.py
jmpy/log.py
jmpy3-1.0.6.dist-info/LICENSE
jmpy3-1.0.6.dist-info/METADATA
jmpy3-1.0.6.dist-info/WHEEL
jmpy3-1.0.6.dist-info/entry_points.txt
jmpy3-1.0.6.dist-info/top_level.txt
jmpy3-1.0.6.dist-info/RECORD
