Metadata-Version: 2.1
Name: jmpy3
Version: 1.0.6
Summary: python代码一键加密
Home-page: https://github.com/Boris-code/jmpy.git
Author: Boris
Author-email: boris@bzkj.tech
License: MIT
Platform: UNKNOWN
Classifier: Programming Language :: Python :: 3
Requires-Dist: Cython (==0.29.20)
